config.py
heuristics.py
main.py
manifest_patcher.py
metrics.py
patcher.py
scanner.py
limitwarden-0.1.0.dist-info/licenses/LICENSE
utils/__init__.py
utils/container_utils.py
utils/utils.py
limitwarden-0.1.0.dist-info/METADATA
limitwarden-0.1.0.dist-info/WHEEL
limitwarden-0.1.0.dist-info/entry_points.txt
limitwarden-0.1.0.dist-info/top_level.txt
limitwarden-0.1.0.dist-info/RECORD
