Metadata-Version: 2.4
Name: limitwarden
Version: 0.1.0
Summary: LimitWarden: Kubernetes resource hygiene enforcer
Home-page: https://github.com/mariedevops/limitwarden
Author: Marie Grin
Classifier: Programming Language :: Python :: 3
Classifier: License :: OSI Approved :: MIT License
Requires-Python: >=3.7
License-File: LICENSE
Requires-Dist: kubernetes
Requires-Dist: PyYAML
Requires-Dist: requests
Dynamic: author
Dynamic: classifier
Dynamic: description
Dynamic: description-content-type
Dynamic: home-page
Dynamic: license-file
Dynamic: requires-dist
Dynamic: requires-python
Dynamic: summary
